remora/__init__.py
remora/remora.py
pyremora-0.5.dist-info/LICENSE
pyremora-0.5.dist-info/METADATA
pyremora-0.5.dist-info/WHEEL
pyremora-0.5.dist-info/top_level.txt
pyremora-0.5.dist-info/RECORD
