Metadata-Version: 2.1
Name: pyremora
Version: 0.5
Summary: A Python library to use the Remora API (Fil Pilote)
Author-email: FreeTHX <freethx.dev@gmail.com>
License: Apache License 2.0
Project-URL: home, https://github.com/FreeTHX/pyremora
Project-URL: repository, https://github.com/FreeTHX/pyremora
Keywords: remora,fil,pilote
Classifier: Development Status :: 3 - Alpha
Classifier: Intended Audience :: Developers
Classifier: Topic :: Home Automation
Classifier: Topic :: Software Development :: Libraries :: Python Modules
Classifier: License :: OSI Approved :: Apache Software License
Classifier: Programming Language :: Python :: 3.7
Requires-Python: >=3.7
License-File: LICENSE
Requires-Dist: aiohttp
